skinpy-0.0.4.dist-info/METADATA
skinpy-0.0.4.dist-info/WHEEL
skinpy-0.0.4.dist-info/entry_points.txt
skinpy/__init__.py
skinpy/__main__.py
skinpy/exception.py
skinpy/render.py
skinpy/skin.py
skinpy/types.py
skinpy-0.0.4.dist-info/RECORD
