Metadata-Version: 2.1
Name: skinpy
Version: 0.0.4
Summary: A Python library for Minecraft skins
Author-Email: Tim Martin <tim@timmart.in>, Steven Van Ingelgem <steven@vaningelgem.be>
License: MIT
Classifier: Programming Language :: Python :: 3.9
Classifier: Programming Language :: Python :: 3.10
Classifier: Programming Language :: Python :: 3.11
Classifier: Programming Language :: Python :: 3.12
Classifier: License :: OSI Approved :: MIT License
Project-URL: Repository, https://github.com/t-mart/skinpy
Requires-Python: >=3.9
Requires-Dist: attrs
Requires-Dist: numpy
Requires-Dist: Pillow
Requires-Dist: click
